Metadata-Version: 2.1
Name: opticalcv
Version: 2.0.0
Summary: optical character verification
Author: anas.ali
Author-email: anas.ali@pekatvision.com
License: UNKNOWN
Platform: UNKNOWN
